emsuite/__init__.py
emsuite/cli.py
emsuite/core.py
emsuite/tuning.py
emsuite-1.0.2.dist-info/METADATA
emsuite-1.0.2.dist-info/WHEEL
emsuite-1.0.2.dist-info/entry_points.txt
emsuite-1.0.2.dist-info/licenses/LICENSE
emsuite-1.0.2.dist-info/RECORD
