Metadata-Version: 2.4
Name: emsuite
Version: 1.0.2
Summary: Electrostatic Map Suite - A Comprehensive Set of Calculators for Qualifying and Quantifying Electrostatic Interactions and Effects.
License-File: LICENSE
Requires-Python: >=3.11
Requires-Dist: geometric>=1.1
Requires-Dist: numpy
Requires-Dist: pyscf-forge>=1.0.3
Requires-Dist: pyscf>=2.10.0
Requires-Dist: rdkit>=2025.3.5
Requires-Dist: requests
Requires-Dist: vdw-surfgen>=0.5.1
Provides-Extra: gpu
Requires-Dist: cupy-cuda12x==13.6.0; extra == 'gpu'
Requires-Dist: cutensor-cu12==2.0.2; extra == 'gpu'
Requires-Dist: gpu4pyscf-cuda12x==1.4.3; extra == 'gpu'
Requires-Dist: gpu4pyscf-libxc-cuda12x==0.5; extra == 'gpu'
